acrcloud/__init__.py
acrcloud/acrcloud_extr_tool.so
acrcloud/recognizer.py
pyacrcloud-1.0.11.dist-info/METADATA
pyacrcloud-1.0.11.dist-info/WHEEL
pyacrcloud-1.0.11.dist-info/top_level.txt
pyacrcloud-1.0.11.dist-info/RECORD
