Metadata-Version: 2.1
Name: pyacrcloud
Version: 1.0.11
Summary: Python wrapper for acrcloud libraries
Home-page: https://github.com/acrcloud/acrcloud_sdk_python
Author: ACRCloud
Author-email: support@acrcloud.com
License: MIT
Keywords: ACRCLoud Python SDK
Platform: macos
